ineapy/__init__.py
ineapy/ine_consultor.py
ineapy/ine_wrapper.py
ineapy-0.1.3.dist-info/LICENSE
ineapy-0.1.3.dist-info/METADATA
ineapy-0.1.3.dist-info/WHEEL
ineapy-0.1.3.dist-info/RECORD
