Metadata-Version: 2.1
Name: ineapy
Version: 0.1.3
Summary: Python library for accessing Spanish National Statistics Institute (INE) data
Home-page: https://github.com/Angel-RC/ineapy.git
License: MIT
Keywords: INE,statistics,data,Spain,API
Author: Angel Rodriguez Chicote
Requires-Python: >=3.9,<3.14
Classifier: License :: OSI Approved :: MIT License
Classifier: Programming Language :: Python :: 3
Classifier: Programming Language :: Python :: 3.9
Classifier: Programming Language :: Python :: 3.10
Classifier: Programming Language :: Python :: 3.11
Classifier: Programming Language :: Python :: 3.12
Requires-Dist: dlt (>=1.9.0,<2.0.0)
Requires-Dist: pandas (>=2.2.3,<3.0.0)
Project-URL: Repository, https://github.com/Angel-RC/ineapy.git
